AUTHORS.txt
INSTALL.md
LICENSE
MANIFEST.in
README.md
bower.json
requirements.txt
setup.cfg
setup.py
requirements/base.txt
requirements/dev.txt
requirements/production.txt
requirements/test.txt
scripts/html2latex_webkit2png.py
src/html2latex/__init__.py
src/html2latex/html2latex.py
src/html2latex/setup_texenv.py
src/html2latex/webkit2png.py
src/html2latex.egg-info/PKG-INFO
src/html2latex.egg-info/SOURCES.txt
src/html2latex.egg-info/dependency_links.txt
src/html2latex.egg-info/namespace_packages.txt
src/html2latex.egg-info/not-zip-safe
src/html2latex.egg-info/pbr.json
src/html2latex.egg-info/requires.txt
src/html2latex.egg-info/top_level.txt
src/html2latex/static/bower_components/MathJax/docs/html/index.html
src/html2latex/static/bower_components/MathJax/test/examples.html
src/html2latex/static/bower_components/MathJax/test/index-images.html
src/html2latex/static/bower_components/MathJax/test/index.html
src/html2latex/static/bower_components/MathJax/test/localization.html
src/html2latex/static/bower_components/MathJax/test/sample-all-at-once.html
src/html2latex/static/bower_components/MathJax/test/sample-asciimath.html
src/html2latex/static/bower_components/MathJax/test/sample-autoload.html
src/html2latex/static/bower_components/MathJax/test/sample-dynamic-2.html
src/html2latex/static/bower_components/MathJax/test/sample-dynamic-steps.html
src/html2latex/static/bower_components/MathJax/test/sample-dynamic.html
src/html2latex/static/bower_components/MathJax/test/sample-eqnum.html
src/html2latex/static/bower_components/MathJax/test/sample-eqrefs.html
src/html2latex/static/bower_components/MathJax/test/sample-loader-config.html
src/html2latex/static/bower_components/MathJax/test/sample-loader.html
src/html2latex/static/bower_components/MathJax/test/sample-macros.html
src/html2latex/static/bower_components/MathJax/test/sample-mml.html
src/html2latex/static/bower_components/MathJax/test/sample-signals.html
src/html2latex/static/bower_components/MathJax/test/sample-tex.html
src/html2latex/static/bower_components/MathJax/test/sample.html
src/html2latex/static/bower_components/sass-bootstrap/about.html
src/html2latex/static/bower_components/sass-bootstrap/components.html
src/html2latex/static/bower_components/sass-bootstrap/css.html
