Metadata-Version: 1.1
Name: html2latex
Version: 0.0.76
Summary: Convert HTML to latex.
Home-page: https://github.com/psjinx/html2latex
Author: Pankaj Singh
Author-email: pankaj@xamcheck.com
License: BSD
Keywords: html,latex
Platform: UNKNOWN
Classifier: Development Status :: 3 - Alpha
Classifier: Topic :: Utilities
Classifier: License :: OSI Approved :: BSD License
